gdf_formatter/__init__.py
gdf_formatter/edge.py
gdf_formatter/graph.py
gdf_formatter/node.py
gdf_formatter-1.0.1.dist-info/METADATA
gdf_formatter-1.0.1.dist-info/RECORD
gdf_formatter-1.0.1.dist-info/WHEEL
gdf_formatter-1.0.1.dist-info/top_level.txt
