Metadata-Version: 2.1
Name: gdf-formatter
Version: 1.0.1
Summary: GDF formatter for networks representation
Home-page: https://github.com/GabrielTrettel/GDF_Formatter
Author: Gabriel Martins Trettel
Author-email: gabrielmtrettel@gmail.com
License: UNKNOWN
Platform: UNKNOWN
Classifier: Programming Language :: Python :: 3.7
Classifier: License :: OSI Approved :: Mozilla Public License 2.0 (MPL 2.0)
Classifier: Operating System :: OS Independent
Classifier: Natural Language :: English
